<nfeProc versao="4.00" xmlns="http://www.portalfiscal.inf.br/nfe"><NFe xmlns="http://www.portalfiscal.inf.br/nfe"><infNFe Id="NFe53211003261204000336550010027366711491155622" versao="4.00"><ide><cUF>53</cUF><cNF>49115562</cNF><natOp>VENDA DE MERC. ADQUIRIDA OU RECEBIDA DE TERCEIROS</natOp><mod>55</mod><serie>1</serie><nNF>2736671</nNF><dhEmi>2021-10-03T10:09:00-03:00</dhEmi><dhSaiEnt>2021-10-03T10:09:00-03:00</dhSaiEnt><tpNF>1</tpNF><idDest>2</idDest><cMunFG>5300108</cMunFG><tpImp>1</tpImp><tpEmis>1</tpEmis><cDV>2</cDV><tpAmb>1</tpAmb><finNFe>1</finNFe><indFinal>0</indFinal><indPres>9</indPres><indIntermed>0</indIntermed><procEmi>0</procEmi><verProc>1.3.198</verProc></ide><emit><CNPJ>03261204000336</CNPJ><xNome>CONDOR ATACADISTA DE MAT P CONSTRUCAO</xNome><xFant>CONDOR ATACADISTA DE MAT P CONSTRUC?O</xFant><enderEmit><xLgr>SIA TR 02 LT 1630/1740 TR 01 LT 1610/40</xLgr><nro>0</nro><xBairro>SIA</xBairro><cMun>5300108</cMun><xMun>BRASILIA (DF)</xMun><UF>DF</UF><CEP>71200020</CEP><cPais>1058</cPais><xPais>BRASIL</xPais><fone>6121078800</fone></enderEmit><IE>0740510600208</IE><IEST>294902996</IEST><CRT>3</CRT></emit><dest><CNPJ>34079845000136</CNPJ><xNome>FERRAGISTA SUPER REI EIRELI</xNome><enderDest><xLgr>Q 706 SUL AVENIDA LO 19 LT 05 SL 01</xLgr><nro>0</nro><xBairro>PLANO DIRETOR SUL</xBairro><cMun>1721000</cMun><xMun>PALMAS (TO)</xMun><UF>TO</UF><CEP>77022414</CEP><cPais>1058</cPais><xPais>BRASIL</xPais><fone>6333220354</fone></enderDest><indIEDest>1</indIEDest><IE>294962476</IE><email>ferragistasuperrei@gmail.com</email></dest><entrega><CNPJ>34079845000136</CNPJ><xLgr>Q 706 SUL AVENIDA LO 19 LT 05 SL 01</xLgr><nro>SN</nro><xBairro>PLANO DIRETOR SUL</xBairro><cMun>1721000</cMun><xMun>PALMAS (TO)</xMun><UF>TO</UF><CEP>77022414</CEP></entrega><det nItem="1"><prod><cProd>63447</cProd><cEAN>7892948000814</cEAN><xProd>SELADORA P/MAD 900ML IQUINE NATURAL</xProd><NCM>32089021</NCM><CEST>2400100</CEST><indEscala>S</indEscala><CFOP>6404</CFOP><uCom>LT</uCom><qCom>6.0000</qCom><vUnCom>16.4800000000</vUnCom><vProd>98.88</vProd><cEANTrib>7892948000814</cEANTrib><uTrib>LT</uTrib><qTrib>6.0000</qTrib><vUnTrib>16.4800000000</vUnTrib><vOutro>0.24</vOutro><indTot>1</indTot><xPed>6787011444</xPed><nItemPed>1</nItemPed></prod><imposto><ICMS><ICMS10><orig>0</orig><CST>10</CST><modBC>3</modBC><vBC>99.12</vBC><pICMS>12.0000</pICMS><vICMS>11.89</vICMS><modBCST>4</modBCST><pMVAST>44.8800</pMVAST><pRedBCST>0.0000</pRedBCST><vBCST>143.64</vBCST><pICMSST>18.0000</pICMSST><vICMSST>13.98</vICMSST></ICMS10></ICMS><IPI><cEnq>999</cEnq><IPITrib><CST>99</CST><vBC>0.00</vBC><pIPI>0.0000</pIPI><vIPI>0.00</vIPI></IPITrib></IPI><PIS><PISAliq><CST>01</CST><vBC>87.23</vBC><pPIS>1.6500</pPIS><vPIS>1.44</vPIS></PISAliq></PIS><COFINS><COFINSAliq><CST>01</CST><vBC>87.23</vBC><pCOFINS>7.6000</pCOFINS><vCOFINS>6.63</vCOFINS></COFINSAliq></COFINS></imposto></det><det nItem="2"><prod><cProd>64404</cProd><cEAN>7892948000180</cEAN><xProd>VERNIZ EXTRARRAPIDO BRIL 900ML IMBUIA</xProd><NCM>32081010</NCM><CEST>2400100</CEST><indEscala>S</indEscala><CFOP>6404</CFOP><uCom>LT</uCom><qCom>6.0000</qCom><vUnCom>18.6600000000</vUnCom><vProd>111.96</vProd><cEANTrib>7892948000180</cEANTrib><uTrib>LT</uTrib><qTrib>6.0000</qTrib><vUnTrib>18.6600000000</vUnTrib><vOutro>0.27</vOutro><indTot>1</indTot><xPed>6787011444</xPed><nItemPed>2</nItemPed></prod><imposto><ICMS><ICMS10><orig>0</orig><CST>10</CST><modBC>3</modBC><vBC>112.23</vBC><pICMS>12.0000</pICMS><vICMS>13.47</vICMS><modBCST>4</modBCST><pMVAST>44.8800</pMVAST><pRedBCST>0.0000</pRedBCST><vBCST>162.54</vBCST><pICMSST>18.0000</pICMSST><vICMSST>15.78</vICMSST></ICMS10></ICMS><IPI><cEnq>999</cEnq><IPITrib><CST>99</CST><vBC>0.00</vBC><pIPI>0.0000</pIPI><vIPI>0.00</vIPI></IPITrib></IPI><PIS><PISAliq><CST>01</CST><vBC>98.76</vBC><pPIS>1.6500</pPIS><vPIS>1.63</vPIS></PISAliq></PIS><COFINS><COFINSAliq><CST>01</CST><vBC>98.76</vBC><pCOFINS>7.6000</pCOFINS><vCOFINS>7.51</vCOFINS></COFINSAliq></COFINS></imposto></det><det nItem="3"><prod><cProd>64405</cProd><cEAN>7892948000395</cEAN><xProd>VERNIZ EXTRARRAPIDO BRIL 900ML MOGNO</xProd><NCM>32081010</NCM><CEST>2400100</CEST><indEscala>S</indEscala><CFOP>6404</CFOP><uCom>LT</uCom><qCom>6.0000</qCom><vUnCom>18.6600000000</vUnCom><vProd>111.96</vProd><cEANTrib>7892948000395</cEANTrib><uTrib>LT</uTrib><qTrib>6.0000</qTrib><vUnTrib>18.6600000000</vUnTrib><vOutro>0.27</vOutro><indTot>1</indTot><xPed>6787011444</xPed><nItemPed>3</nItemPed></prod><imposto><ICMS><ICMS10><orig>0</orig><CST>10</CST><modBC>3</modBC><vBC>112.23</vBC><pICMS>12.0000</pICMS><vICMS>13.47</vICMS><modBCST>4</modBCST><pMVAST>44.8800</pMVAST><pRedBCST>0.0000</pRedBCST><vBCST>162.54</vBCST><pICMSST>18.0000</pICMSST><vICMSST>15.78</vICMSST></ICMS10></ICMS><IPI><cEnq>999</cEnq><IPITrib><CST>99</CST><vBC>0.00</vBC><pIPI>0.0000</pIPI><vIPI>0.00</vIPI></IPITrib></IPI><PIS><PISAliq><CST>01</CST><vBC>98.76</vBC><pPIS>1.6500</pPIS><vPIS>1.63</vPIS></PISAliq></PIS><COFINS><COFINSAliq><CST>01</CST><vBC>98.76</vBC><pCOFINS>7.6000</pCOFINS><vCOFINS>7.51</vCOFINS></COFINSAliq></COFINS></imposto></det><det nItem="4"><prod><cProd>71736</cProd><cEAN>7898918041368</cEAN><xProd>TOMADA EM BARRA 2P+T TRIPLA 10A BR</xProd><NCM>85366990</NCM><CFOP>6102</CFOP><uCom>UN</uCom><qCom>3.0000</qCom><vUnCom>7.9800000000</vUnCom><vProd>23.94</vProd><cEANTrib>7898918041368</cEANTrib><uTrib>UN</uTrib><qTrib>3.0000</qTrib><vUnTrib>7.9800000000</vUnTrib><vOutro>0.05</vOutro><indTot>1</indTot><xPed>6787011444</xPed><nItemPed>4</nItemPed></prod><imposto><ICMS><ICMS00><orig>0</orig><CST>00</CST><modBC>3</modBC><vBC>23.99</vBC><pICMS>12.0000</pICMS><vICMS>2.88</vICMS></ICMS00></ICMS><IPI><cEnq>999</cEnq><IPITrib><CST>99</CST><vBC>0.00</vBC><pIPI>0.0000</pIPI><vIPI>0.00</vIPI></IPITrib></IPI><PIS><PISAliq><CST>01</CST><vBC>21.11</vBC><pPIS>1.6500</pPIS><vPIS>0.35</vPIS></PISAliq></PIS><COFINS><COFINSAliq><CST>01</CST><vBC>21.11</vBC><pCOFINS>7.6000</pCOFINS><vCOFINS>1.60</vCOFINS></COFINSAliq></COFINS></imposto></det><det nItem="5"><prod><cProd>71737</cProd><cEAN>7898918041375</cEAN><xProd>TOMADA EM BARRA 2P+T QUADRUPLA 10A BR</xProd><NCM>85366990</NCM><CFOP>6102</CFOP><uCom>UN</uCom><qCom>3.0000</qCom><vUnCom>9.5900000000</vUnCom><vProd>28.77</vProd><cEANTrib>7898918041375</cEANTrib><uTrib>UN</uTrib><qTrib>3.0000</qTrib><vUnTrib>9.5900000000</vUnTrib><vOutro>0.06</vOutro><indTot>1</indTot><xPed>6787011444</xPed><nItemPed>5</nItemPed></prod><imposto><ICMS><ICMS00><orig>0</orig><CST>00</CST><modBC>3</modBC><vBC>28.83</vBC><pICMS>12.0000</pICMS><vICMS>3.46</vICMS></ICMS00></ICMS><IPI><cEnq>999</cEnq><IPITrib><CST>99</CST><vBC>0.00</vBC><pIPI>0.0000</pIPI><vIPI>0.00</vIPI></IPITrib></IPI><PIS><PISAliq><CST>01</CST><vBC>25.37</vBC><pPIS>1.6500</pPIS><vPIS>0.42</vPIS></PISAliq></PIS><COFINS><COFINSAliq><CST>01</CST><vBC>25.37</vBC><pCOFINS>7.6000</pCOFINS><vCOFINS>1.93</vCOFINS></COFINSAliq></COFINS></imposto></det><det nItem="6"><prod><cProd>71738</cProd><cEAN>7898918041382</cEAN><xProd>TOMADA EM BARRA 2P+T QUINTUPLA 10A BR</xProd><NCM>85366990</NCM><CFOP>6102</CFOP><uCom>UN</uCom><qCom>2.0000</qCom><vUnCom>10.9700000000</vUnCom><vProd>21.94</vProd><cEANTrib>7898918041382</cEANTrib><uTrib>UN</uTrib><qTrib>2.0000</qTrib><vUnTrib>10.9700000000</vUnTrib><vOutro>0.04</vOutro><indTot>1</indTot><xPed>6787011444</xPed><nItemPed>6</nItemPed></prod><imposto><ICMS><ICMS00><orig>0</orig><CST>00</CST><modBC>3</modBC><vBC>21.98</vBC><pICMS>12.0000</pICMS><vICMS>2.64</vICMS></ICMS00></ICMS><IPI><cEnq>999</cEnq><IPITrib><CST>99</CST><vBC>0.00</vBC><pIPI>0.0000</pIPI><vIPI>0.00</vIPI></IPITrib></IPI><PIS><PISAliq><CST>01</CST><vBC>19.34</vBC><pPIS>1.6500</pPIS><vPIS>0.32</vPIS></PISAliq></PIS><COFINS><COFINSAliq><CST>01</CST><vBC>19.34</vBC><pCOFINS>7.6000</pCOFINS><vCOFINS>1.47</vCOFINS></COFINSAliq></COFINS></imposto></det><det nItem="7"><prod><cProd>73098</cProd><cEAN>7898338093787</cEAN><xProd>SERRA CIRC DE WIDEA 184MM (7.1/4") 24D</xProd><NCM>82023900</NCM><CFOP>6102</CFOP><uCom>UN</uCom><qCom>2.0000</qCom><vUnCom>15.2400000000</vUnCom><vProd>30.48</vProd><cEANTrib>7898338093787</cEANTrib><uTrib>UN</uTrib><qTrib>2.0000</qTrib><vUnTrib>15.2400000000</vUnTrib><vOutro>0.06</vOutro><indTot>1</indTot><xPed>6787011444</xPed><nItemPed>7</nItemPed></prod><imposto><ICMS><ICMS00><orig>2</orig><CST>00</CST><modBC>3</modBC><vBC>30.54</vBC><pICMS>4.0000</pICMS><vICMS>1.22</vICMS></ICMS00></ICMS><IPI><cEnq>999</cEnq><IPITrib><CST>99</CST><vBC>0.00</vBC><pIPI>0.0000</pIPI><vIPI>0.00</vIPI></IPITrib></IPI><PIS><PISAliq><CST>01</CST><vBC>29.32</vBC><pPIS>1.6500</pPIS><vPIS>0.48</vPIS></PISAliq></PIS><COFINS><COFINSAliq><CST>01</CST><vBC>29.32</vBC><pCOFINS>7.6000</pCOFINS><vCOFINS>2.23</vCOFINS></COFINSAliq></COFINS></imposto></det><det nItem="8"><prod><cProd>70315</cProd><cEAN>7898547051103</cEAN><xProd>SERRA CIRC DE WIDEA 110MM (4.3/8") 24D</xProd><NCM>82023100</NCM><CFOP>6102</CFOP><uCom>UN</uCom><qCom>6.0000</qCom><vUnCom>7.1100000000</vUnCom><vProd>42.66</vProd><cEANTrib>7898547051103</cEANTrib><uTrib>UN</uTrib><qTrib>6.0000</qTrib><vUnTrib>7.1100000000</vUnTrib><vOutro>0.09</vOutro><indTot>1</indTot><xPed>6787011444</xPed><nItemPed>8</nItemPed></prod><imposto><ICMS><ICMS00><orig>2</orig><CST>00</CST><modBC>3</modBC><vBC>42.75</vBC><pICMS>4.0000</pICMS><vICMS>1.71</vICMS></ICMS00></ICMS><IPI><cEnq>999</cEnq><IPITrib><CST>99</CST><vBC>0.00</vBC><pIPI>0.0000</pIPI><vIPI>0.00</vIPI></IPITrib></IPI><PIS><PISAliq><CST>01</CST><vBC>41.04</vBC><pPIS>1.6500</pPIS><vPIS>0.68</vPIS></PISAliq></PIS><COFINS><COFINSAliq><CST>01</CST><vBC>41.04</vBC><pCOFINS>7.6000</pCOFINS><vCOFINS>3.12</vCOFINS></COFINSAliq></COFINS></imposto></det><det nItem="9"><prod><cProd>75879</cProd><cEAN>7899612707062</cEAN><xProd>LAMINA P/ESTILETE 18MM 10PC</xProd><NCM>82119400</NCM><CFOP>6102</CFOP><uCom>UN</uCom><qCom>10.0000</qCom><vUnCom>2.1900000000</vUnCom><vProd>21.90</vProd><cEANTrib>7899612707062</cEANTrib><uTrib>UN</uTrib><qTrib>10.0000</qTrib><vUnTrib>2.1900000000</vUnTrib><vOutro>0.04</vOutro><indTot>1</indTot><xPed>6787011444</xPed><nItemPed>9</nItemPed></prod><imposto><ICMS><ICMS00><orig>2</orig><CST>00</CST><modBC>3</modBC><vBC>21.94</vBC><pICMS>4.0000</pICMS><vICMS>0.88</vICMS></ICMS00></ICMS><IPI><cEnq>999</cEnq><IPITrib><CST>99</CST><vBC>0.00</vBC><pIPI>0.0000</pIPI><vIPI>0.00</vIPI></IPITrib></IPI><PIS><PISAliq><CST>01</CST><vBC>21.06</vBC><pPIS>1.6500</pPIS><vPIS>0.35</vPIS></PISAliq></PIS><COFINS><COFINSAliq><CST>01</CST><vBC>21.06</vBC><pCOFINS>7.6000</pCOFINS><vCOFINS>1.60</vCOFINS></COFINSAliq></COFINS></imposto></det><det nItem="10"><prod><cProd>62763</cProd><cEAN>7898427446838</cEAN><xProd>CONECTOR DERIVACAO PERFURANTE 70MM</xProd><NCM>85359090</NCM><CEST>1200300</CEST><indEscala>S</indEscala><CFOP>6102</CFOP><uCom>UN</uCom><qCom>4.0000</qCom><vUnCom>6.9800000000</vUnCom><vProd>27.92</vProd><cEANTrib>7898427446838</cEANTrib><uTrib>UN</uTrib><qTrib>4.0000</qTrib><vUnTrib>6.9800000000</vUnTrib><vOutro>0.06</vOutro><indTot>1</indTot><xPed>6787011444</xPed><nItemPed>10</nItemPed></prod><imposto><ICMS><ICMS00><orig>0</orig><CST>00</CST><modBC>3</modBC><vBC>27.98</vBC><pICMS>12.0000</pICMS><vICMS>3.36</vICMS></ICMS00></ICMS><IPI><cEnq>999</cEnq><IPITrib><CST>99</CST><vBC>0.00</vBC><pIPI>0.0000</pIPI><vIPI>0.00</vIPI></IPITrib></IPI><PIS><PISAliq><CST>01</CST><vBC>24.62</vBC><pPIS>1.6500</pPIS><vPIS>0.41</vPIS></PISAliq></PIS><COFINS><COFINSAliq><CST>01</CST><vBC>24.62</vBC><pCOFINS>7.6000</pCOFINS><vCOFINS>1.87</vCOFINS></COFINSAliq></COFINS></imposto></det><det nItem="11"><prod><cProd>67495</cProd><cEAN>5411183139442</cEAN><xProd>ESPUMA EXPANSIVA PU 500ML 340GR</xProd><NCM>32141010</NCM><CFOP>6102</CFOP><uCom>FR</uCom><qCom>3.0000</qCom><vUnCom>13.4600000000</vUnCom><vProd>40.38</vProd><cEANTrib>5411183139442</cEANTrib><uTrib>FR</uTrib><qTrib>3.0000</qTrib><vUnTrib>13.4600000000</vUnTrib><vOutro>0.08</vOutro><indTot>1</indTot><xPed>6787011444</xPed><nItemPed>11</nItemPed></prod><imposto><ICMS><ICMS00><orig>2</orig><CST>00</CST><modBC>3</modBC><vBC>40.46</vBC><pICMS>4.0000</pICMS><vICMS>1.62</vICMS></ICMS00></ICMS><IPI><cEnq>999</cEnq><IPITrib><CST>99</CST><vBC>0.00</vBC><pIPI>0.0000</pIPI><vIPI>0.00</vIPI></IPITrib></IPI><PIS><PISAliq><CST>01</CST><vBC>38.84</vBC><pPIS>1.6500</pPIS><vPIS>0.64</vPIS></PISAliq></PIS><COFINS><COFINSAliq><CST>01</CST><vBC>38.84</vBC><pCOFINS>7.6000</pCOFINS><vCOFINS>2.95</vCOFINS></COFINSAliq></COFINS></imposto></det><det nItem="12"><prod><cProd>75014</cProd><cEAN>7899612796004</cEAN><xProd>PE DE CABRA 1" 60CM PT SEXTAVADO</xProd><NCM>82055900</NCM><CFOP>6102</CFOP><uCom>UN</uCom><qCom>3.0000</qCom><vUnCom>22.9600000000</vUnCom><vProd>68.88</vProd><cEANTrib>7899612796004</cEANTrib><uTrib>UN</uTrib><qTrib>3.0000</qTrib><vUnTrib>22.9600000000</vUnTrib><vOutro>0.15</vOutro><indTot>1</indTot><xPed>6787011444</xPed><nItemPed>12</nItemPed></prod><imposto><ICMS><ICMS00><orig>2</orig><CST>00</CST><modBC>3</modBC><vBC>69.03</vBC><pICMS>4.0000</pICMS><vICMS>2.76</vICMS></ICMS00></ICMS><IPI><cEnq>999</cEnq><IPITrib><CST>99</CST><vBC>0.00</vBC><pIPI>0.0000</pIPI><vIPI>0.00</vIPI></IPITrib></IPI><PIS><PISAliq><CST>01</CST><vBC>66.27</vBC><pPIS>1.6500</pPIS><vPIS>1.09</vPIS></PISAliq></PIS><COFINS><COFINSAliq><CST>01</CST><vBC>66.27</vBC><pCOFINS>7.6000</pCOFINS><vCOFINS>5.04</vCOFINS></COFINSAliq></COFINS></imposto></det><det nItem="13"><prod><cProd>70587</cProd><cEAN>7896689110368</cEAN><xProd>SUPORTE P/MICROONDAS CONVENC BRANCO</xProd><NCM>73269090</NCM><CFOP>6102</CFOP><uCom>UN</uCom><qCom>3.0000</qCom><vUnCom>21.6000000000</vUnCom><vProd>64.80</vProd><cEANTrib>7896689110368</cEANTrib><uTrib>UN</uTrib><qTrib>3.0000</qTrib><vUnTrib>21.6000000000</vUnTrib><vOutro>0.14</vOutro><indTot>1</indTot><xPed>6787011444</xPed><nItemPed>13</nItemPed></prod><imposto><ICMS><ICMS00><orig>0</orig><CST>00</CST><modBC>3</modBC><vBC>64.94</vBC><pICMS>12.0000</pICMS><vICMS>7.79</vICMS></ICMS00></ICMS><IPI><cEnq>999</cEnq><IPITrib><CST>99</CST><vBC>0.00</vBC><pIPI>0.0000</pIPI><vIPI>0.00</vIPI></IPITrib></IPI><PIS><PISAliq><CST>01</CST><vBC>57.15</vBC><pPIS>1.6500</pPIS><vPIS>0.94</vPIS></PISAliq></PIS><COFINS><COFINSAliq><CST>01</CST><vBC>57.15</vBC><pCOFINS>7.6000</pCOFINS><vCOFINS>4.34</vCOFINS></COFINSAliq></COFINS></imposto></det><det nItem="14"><prod><cProd>54602</cProd><cEAN>7896202400013</cEAN><xProd>DESENTUPIDOR TUFAO I C/5M</xProd><NCM>82055900</NCM><CEST>0801000</CEST><indEscala>S</indEscala><CFOP>6102</CFOP><uCom>UN</uCom><qCom>1.0000</qCom><vUnCom>25.5200000000</vUnCom><vProd>25.52</vProd><cEANTrib>7896202400013</cEANTrib><uTrib>UN</uTrib><qTrib>1.0000</qTrib><vUnTrib>25.5200000000</vUnTrib><vOutro>0.05</vOutro><indTot>1</indTot><xPed>6787011444</xPed><nItemPed>14</nItemPed></prod><imposto><ICMS><ICMS00><orig>0</orig><CST>00</CST><modBC>3</modBC><vBC>25.57</vBC><pICMS>12.0000</pICMS><vICMS>3.07</vICMS></ICMS00></ICMS><IPI><cEnq>999</cEnq><IPITrib><CST>99</CST><vBC>0.00</vBC><pIPI>0.0000</pIPI><vIPI>0.00</vIPI></IPITrib></IPI><PIS><PISAliq><CST>01</CST><vBC>22.50</vBC><pPIS>1.6500</pPIS><vPIS>0.37</vPIS></PISAliq></PIS><COFINS><COFINSAliq><CST>01</CST><vBC>22.50</vBC><pCOFINS>7.6000</pCOFINS><vCOFINS>1.71</vCOFINS></COFINSAliq></COFINS></imposto></det><det nItem="15"><prod><cProd>74468</cProd><cEAN>7899612780577</cEAN><xProd>REBOLO DIAM TURBO 110MM</xProd><NCM>68042119</NCM><CFOP>6102</CFOP><uCom>UN</uCom><qCom>1.0000</qCom><vUnCom>42.7100000000</vUnCom><vProd>42.71</vProd><cEANTrib>7899612780577</cEANTrib><uTrib>UN</uTrib><qTrib>1.0000</qTrib><vUnTrib>42.7100000000</vUnTrib><vOutro>0.09</vOutro><indTot>1</indTot><xPed>6787011444</xPed><nItemPed>15</nItemPed></prod><imposto><ICMS><ICMS00><orig>2</orig><CST>00</CST><modBC>3</modBC><vBC>42.80</vBC><pICMS>4.0000</pICMS><vICMS>1.71</vICMS></ICMS00></ICMS><IPI><cEnq>999</cEnq><IPITrib><CST>99</CST><vBC>0.00</vBC><pIPI>0.0000</pIPI><vIPI>0.00</vIPI></IPITrib></IPI><PIS><PISAliq><CST>01</CST><vBC>41.09</vBC><pPIS>1.6500</pPIS><vPIS>0.68</vPIS></PISAliq></PIS><COFINS><COFINSAliq><CST>01</CST><vBC>41.09</vBC><pCOFINS>7.6000</pCOFINS><vCOFINS>3.12</vCOFINS></COFINSAliq></COFINS></imposto></det><det nItem="16"><prod><cProd>73086</cProd><cEAN>7898338090236</cEAN><xProd>ALICATE AMPERIMETRO C/ESTOJO E BATERIA</xProd><NCM>90303329</NCM><CFOP>6102</CFOP><uCom>UN</uCom><qCom>2.0000</qCom><vUnCom>40.2000000000</vUnCom><vProd>80.40</vProd><cEANTrib>7898338090236</cEANTrib><uTrib>UN</uTrib><qTrib>2.0000</qTrib><vUnTrib>40.2000000000</vUnTrib><vOutro>0.17</vOutro><indTot>1</indTot><xPed>6787011444</xPed><nItemPed>16</nItemPed></prod><imposto><ICMS><ICMS00><orig>2</orig><CST>00</CST><modBC>3</modBC><vBC>80.57</vBC><pICMS>4.0000</pICMS><vICMS>3.22</vICMS></ICMS00></ICMS><IPI><cEnq>999</cEnq><IPITrib><CST>99</CST><vBC>0.00</vBC><pIPI>0.0000</pIPI><vIPI>0.00</vIPI></IPITrib></IPI><PIS><PISAliq><CST>01</CST><vBC>77.35</vBC><pPIS>1.6500</pPIS><vPIS>1.28</vPIS></PISAliq></PIS><COFINS><COFINSAliq><CST>01</CST><vBC>77.35</vBC><pCOFINS>7.6000</pCOFINS><vCOFINS>5.88</vCOFINS></COFINSAliq></COFINS></imposto></det><det nItem="17"><prod><cProd>66158</cProd><cEAN>7898322649570</cEAN><xProd>PLUG 2P+T MACHO CZ 10A PRENSA CABO</xProd><NCM>85369090</NCM><CFOP>6102</CFOP><uCom>UN</uCom><qCom>20.0000</qCom><vUnCom>2.9800000000</vUnCom><vProd>59.60</vProd><cEANTrib>7898322649570</cEANTrib><uTrib>UN</uTrib><qTrib>20.0000</qTrib><vUnTrib>2.9800000000</vUnTrib><vOutro>0.12</vOutro><indTot>1</indTot><xPed>6787011444</xPed><nItemPed>17</nItemPed></prod><imposto><ICMS><ICMS00><orig>0</orig><CST>00</CST><modBC>3</modBC><vBC>59.72</vBC><pICMS>12.0000</pICMS><vICMS>7.17</vICMS></ICMS00></ICMS><IPI><cEnq>999</cEnq><IPITrib><CST>99</CST><vBC>0.00</vBC><pIPI>0.0000</pIPI><vIPI>0.00</vIPI></IPITrib></IPI><PIS><PISAliq><CST>01</CST><vBC>52.55</vBC><pPIS>1.6500</pPIS><vPIS>0.87</vPIS></PISAliq></PIS><COFINS><COFINSAliq><CST>01</CST><vBC>52.55</vBC><pCOFINS>7.6000</pCOFINS><vCOFINS>3.99</vCOFINS></COFINSAliq></COFINS></imposto></det><det nItem="18"><prod><cProd>56818</cProd><cEAN>7898493990341</cEAN><xProd>PLUG 2P MACHO CZ 10A TRIANG</xProd><NCM>85369090</NCM><CEST>1200400</CEST><indEscala>S</indEscala><CFOP>6102</CFOP><uCom>UN</uCom><qCom>20.0000</qCom><vUnCom>1.7900000000</vUnCom><vProd>35.80</vProd><cEANTrib>7898493990341</cEANTrib><uTrib>UN</uTrib><qTrib>20.0000</qTrib><vUnTrib>1.7900000000</vUnTrib><vOutro>0.07</vOutro><indTot>1</indTot><xPed>6787011444</xPed><nItemPed>18</nItemPed></prod><imposto><ICMS><ICMS00><orig>0</orig><CST>00</CST><modBC>3</modBC><vBC>35.87</vBC><pICMS>12.0000</pICMS><vICMS>4.30</vICMS></ICMS00></ICMS><IPI><cEnq>999</cEnq><IPITrib><CST>99</CST><vBC>0.00</vBC><pIPI>0.0000</pIPI><vIPI>0.00</vIPI></IPITrib></IPI><PIS><PISAliq><CST>01</CST><vBC>31.57</vBC><pPIS>1.6500</pPIS><vPIS>0.52</vPIS></PISAliq></PIS><COFINS><COFINSAliq><CST>01</CST><vBC>31.57</vBC><pCOFINS>7.6000</pCOFINS><vCOFINS>2.40</vCOFINS></COFINSAliq></COFINS></imposto></det><det nItem="19"><prod><cProd>52399</cProd><cEAN>4052399001003</cEAN><xProd>CABO MADEIRA PA RETA 1,20M</xProd><NCM>44170010</NCM><CEST>0800200</CEST><indEscala>S</indEscala><CFOP>6102</CFOP><uCom>UN</uCom><qCom>5.0000</qCom><vUnCom>5.0000000000</vUnCom><vProd>25.00</vProd><cEANTrib>4052399001003</cEANTrib><uTrib>UN</uTrib><qTrib>5.0000</qTrib><vUnTrib>5.0000000000</vUnTrib><vOutro>0.05</vOutro><indTot>1</indTot><xPed>6787011444</xPed><nItemPed>19</nItemPed></prod><imposto><ICMS><ICMS00><orig>0</orig><CST>00</CST><modBC>3</modBC><vBC>25.05</vBC><pICMS>12.0000</pICMS><vICMS>3.01</vICMS></ICMS00></ICMS><IPI><cEnq>999</cEnq><IPITrib><CST>99</CST><vBC>0.00</vBC><pIPI>0.0000</pIPI><vIPI>0.00</vIPI></IPITrib></IPI><PIS><PISAliq><CST>01</CST><vBC>22.04</vBC><pPIS>1.6500</pPIS><vPIS>0.36</vPIS></PISAliq></PIS><COFINS><COFINSAliq><CST>01</CST><vBC>22.04</vBC><pCOFINS>7.6000</pCOFINS><vCOFINS>1.68</vCOFINS></COFINSAliq></COFINS></imposto></det><det nItem="20"><prod><cProd>60570</cProd><cEAN>7898101720063</cEAN><xProd>OLEO MULTIUSO TIPO SINGER 100ML</xProd><NCM>27101932</NCM><CEST>0600700</CEST><indEscala>S</indEscala><CFOP>6655</CFOP><uCom>FR</uCom><qCom>5.0000</qCom><vUnCom>2.6400000000</vUnCom><vProd>13.20</vProd><cEANTrib>7898101720063</cEANTrib><uTrib>FR</uTrib><qTrib>5.0000</qTrib><vUnTrib>2.6400000000</vUnTrib><vOutro>0.03</vOutro><indTot>1</indTot><xPed>6787011444</xPed><nItemPed>20</nItemPed><comb><cProdANP>620601004</cProdANP><descANP>OUTROS OLEOS</descANP><UFCons>TO</UFCons></comb></prod><imposto><ICMS><ICMS30><orig>0</orig><CST>30</CST><modBCST>4</modBCST><pMVAST>96.7200</pMVAST><pRedBCST>0.0000</pRedBCST><vBCST>26.00</vBCST><pICMSST>18.0000</pICMSST><vICMSST>4.70</vICMSST></ICMS30></ICMS><IPI><cEnq>999</cEnq><IPITrib><CST>99</CST><vBC>0.00</vBC><pIPI>0.0000</pIPI><vIPI>0.00</vIPI></IPITrib></IPI><PIS><PISAliq><CST>01</CST><vBC>13.23</vBC><pPIS>1.6500</pPIS><vPIS>0.22</vPIS></PISAliq></PIS><COFINS><COFINSAliq><CST>01</CST><vBC>13.23</vBC><pCOFINS>7.6000</pCOFINS><vCOFINS>1.01</vCOFINS></COFINSAliq></COFINS></imposto></det><det nItem="21"><prod><cProd>100245</cProd><cEAN>7898503497594</cEAN><xProd>LUVA SOLDAVEL CORRER 25MM</xProd><NCM>39174090</NCM><CEST>1000600</CEST><indEscala>S</indEscala><CFOP>6102</CFOP><uCom>UN</uCom><qCom>12.0000</qCom><vUnCom>6.9800000000</vUnCom><vProd>83.76</vProd><cEANTrib>7898503497594</cEANTrib><uTrib>UN</uTrib><qTrib>12.0000</qTrib><vUnTrib>6.9800000000</vUnTrib><vOutro>0.18</vOutro><indTot>1</indTot><xPed>6787011444</xPed><nItemPed>21</nItemPed></prod><imposto><ICMS><ICMS00><orig>0</orig><CST>00</CST><modBC>3</modBC><vBC>83.94</vBC><pICMS>12.0000</pICMS><vICMS>10.07</vICMS></ICMS00></ICMS><IPI><cEnq>999</cEnq><IPITrib><CST>99</CST><vBC>0.00</vBC><pIPI>0.0000</pIPI><vIPI>0.00</vIPI></IPITrib></IPI><PIS><PISAliq><CST>01</CST><vBC>73.87</vBC><pPIS>1.6500</pPIS><vPIS>1.22</vPIS></PISAliq></PIS><COFINS><COFINSAliq><CST>01</CST><vBC>73.87</vBC><pCOFINS>7.6000</pCOFINS><vCOFINS>5.61</vCOFINS></COFINSAliq></COFINS></imposto></det><det nItem="22"><prod><cProd>74184</cProd><cEAN>7896202400266</cEAN><xProd>ORGANIZADOR DE FIOS C/1 MT 3/8 BRANCO</xProd><NCM>39173900</NCM><EXTIPI>01</EXTIPI><CFOP>6102</CFOP><uCom>UN</uCom><qCom>3.0000</qCom><vUnCom>2.9500000000</vUnCom><vProd>8.85</vProd><cEANTrib>7896202400266</cEANTrib><uTrib>UN</uTrib><qTrib>3.0000</qTrib><vUnTrib>2.9500000000</vUnTrib><vOutro>0.01</vOutro><indTot>1</indTot><xPed>6787011444</xPed><nItemPed>22</nItemPed></prod><imposto><ICMS><ICMS00><orig>0</orig><CST>00</CST><modBC>3</modBC><vBC>8.86</vBC><pICMS>12.0000</pICMS><vICMS>1.06</vICMS></ICMS00></ICMS><IPI><cEnq>999</cEnq><IPITrib><CST>99</CST><vBC>0.00</vBC><pIPI>0.0000</pIPI><vIPI>0.00</vIPI></IPITrib></IPI><PIS><PISAliq><CST>01</CST><vBC>7.80</vBC><pPIS>1.6500</pPIS><vPIS>0.13</vPIS></PISAliq></PIS><COFINS><COFINSAliq><CST>01</CST><vBC>7.80</vBC><pCOFINS>7.6000</pCOFINS><vCOFINS>0.59</vCOFINS></COFINSAliq></COFINS></imposto></det><det nItem="23"><prod><cProd>74185</cProd><cEAN>7896202400372</cEAN><xProd>ORGANIZADOR DE FIOS C/1 MT 3/8 PRETO</xProd><NCM>39173900</NCM><EXTIPI>01</EXTIPI><CFOP>6102</CFOP><uCom>UN</uCom><qCom>3.0000</qCom><vUnCom>2.9500000000</vUnCom><vProd>8.85</vProd><cEANTrib>7896202400372</cEANTrib><uTrib>UN</uTrib><qTrib>3.0000</qTrib><vUnTrib>2.9500000000</vUnTrib><vOutro>0.01</vOutro><indTot>1</indTot><xPed>6787011444</xPed><nItemPed>23</nItemPed></prod><imposto><ICMS><ICMS00><orig>0</orig><CST>00</CST><modBC>3</modBC><vBC>8.86</vBC><pICMS>12.0000</pICMS><vICMS>1.06</vICMS></ICMS00></ICMS><IPI><cEnq>999</cEnq><IPITrib><CST>99</CST><vBC>0.00</vBC><pIPI>0.0000</pIPI><vIPI>0.00</vIPI></IPITrib></IPI><PIS><PISAliq><CST>01</CST><vBC>7.80</vBC><pPIS>1.6500</pPIS><vPIS>0.13</vPIS></PISAliq></PIS><COFINS><COFINSAliq><CST>01</CST><vBC>7.80</vBC><pCOFINS>7.6000</pCOFINS><vCOFINS>0.59</vCOFINS></COFINSAliq></COFINS></imposto></det><det nItem="24"><prod><cProd>62432</cProd><cEAN>7893946169442</cEAN><xProd>CINTA P/AMARRACAO DE CARGA C/CATR 0,8T 4</xProd><NCM>56079090</NCM><CEST>1007800</CEST><indEscala>S</indEscala><CFOP>6102</CFOP><uCom>CX</uCom><qCom>4.0000</qCom><vUnCom>23.2600000000</vUnCom><vProd>93.04</vProd><cEANTrib>7893946169442</cEANTrib><uTrib>CX</uTrib><qTrib>4.0000</qTrib><vUnTrib>23.2600000000</vUnTrib><vOutro>0.20</vOutro><indTot>1</indTot><xPed>6787011444</xPed><nItemPed>24</nItemPed></prod><imposto><ICMS><ICMS00><orig>2</orig><CST>00</CST><modBC>3</modBC><vBC>93.24</vBC><pICMS>4.0000</pICMS><vICMS>3.73</vICMS></ICMS00></ICMS><IPI><cEnq>999</cEnq><IPITrib><CST>99</CST><vBC>0.00</vBC><pIPI>0.0000</pIPI><vIPI>0.00</vIPI></IPITrib></IPI><PIS><PISAliq><CST>01</CST><vBC>89.51</vBC><pPIS>1.6500</pPIS><vPIS>1.48</vPIS></PISAliq></PIS><COFINS><COFINSAliq><CST>01</CST><vBC>89.51</vBC><pCOFINS>7.6000</pCOFINS><vCOFINS>6.80</vCOFINS></COFINSAliq></COFINS></imposto></det><det nItem="25"><prod><cProd>62433</cProd><cEAN>7893946169466</cEAN><xProd>CINTA P/AMARRACAO DE CARGA C/CATR 1,5T</xProd><NCM>56079090</NCM><CEST>1007800</CEST><indEscala>S</indEscala><CFOP>6102</CFOP><uCom>CX</uCom><qCom>2.0000</qCom><vUnCom>37.9100000000</vUnCom><vProd>75.82</vProd><cEANTrib>7893946169466</cEANTrib><uTrib>CX</uTrib><qTrib>2.0000</qTrib><vUnTrib>37.9100000000</vUnTrib><vOutro>0.16</vOutro><indTot>1</indTot><xPed>6787011444</xPed><nItemPed>25</nItemPed></prod><imposto><ICMS><ICMS00><orig>2</orig><CST>00</CST><modBC>3</modBC><vBC>75.98</vBC><pICMS>4.0000</pICMS><vICMS>3.04</vICMS></ICMS00></ICMS><IPI><cEnq>999</cEnq><IPITrib><CST>99</CST><vBC>0.00</vBC><pIPI>0.0000</pIPI><vIPI>0.00</vIPI></IPITrib></IPI><PIS><PISAliq><CST>01</CST><vBC>72.94</vBC><pPIS>1.6500</pPIS><vPIS>1.20</vPIS></PISAliq></PIS><COFINS><COFINSAliq><CST>01</CST><vBC>72.94</vBC><pCOFINS>7.6000</pCOFINS><vCOFINS>5.54</vCOFINS></COFINSAliq></COFINS></imposto></det><det nItem="26"><prod><cProd>72856</cProd><cEAN>7898575249022</cEAN><xProd>ALICATE CRIMPADOR RJ45</xProd><NCM>82032010</NCM><CFOP>6102</CFOP><uCom>UN</uCom><qCom>2.0000</qCom><vUnCom>21.5200000000</vUnCom><vProd>43.04</vProd><cEANTrib>7898575249022</cEANTrib><uTrib>UN</uTrib><qTrib>2.0000</qTrib><vUnTrib>21.5200000000</vUnTrib><vOutro>0.09</vOutro><indTot>1</indTot><xPed>6787011444</xPed><nItemPed>26</nItemPed></prod><imposto><ICMS><ICMS00><orig>2</orig><CST>00</CST><modBC>3</modBC><vBC>43.13</vBC><pICMS>4.0000</pICMS><vICMS>1.73</vICMS></ICMS00></ICMS><IPI><cEnq>999</cEnq><IPITrib><CST>99</CST><vBC>0.00</vBC><pIPI>0.0000</pIPI><vIPI>0.00</vIPI></IPITrib></IPI><PIS><PISAliq><CST>01</CST><vBC>41.40</vBC><pPIS>1.6500</pPIS><vPIS>0.68</vPIS></PISAliq></PIS><COFINS><COFINSAliq><CST>01</CST><vBC>41.40</vBC><pCOFINS>7.6000</pCOFINS><vCOFINS>3.15</vCOFINS></COFINSAliq></COFINS></imposto></det><det nItem="27"><prod><cProd>63397</cProd><cEAN>7892948024445</cEAN><xProd>TINTA ESM BRIL STD 900ML DELANIL BR</xProd><NCM>32081010</NCM><CEST>2400100</CEST><indEscala>S</indEscala><CFOP>6404</CFOP><uCom>LT</uCom><qCom>6.0000</qCom><vUnCom>13.0000000000</vUnCom><vProd>78.00</vProd><cEANTrib>7892948024445</cEANTrib><uTrib>LT</uTrib><qTrib>6.0000</qTrib><vUnTrib>13.0000000000</vUnTrib><vOutro>0.19</vOutro><indTot>1</indTot><xPed>6787011444</xPed><nItemPed>27</nItemPed></prod><imposto><ICMS><ICMS10><orig>0</orig><CST>10</CST><modBC>3</modBC><vBC>78.19</vBC><pICMS>12.0000</pICMS><vICMS>9.38</vICMS><modBCST>4</modBCST><pMVAST>44.8800</pMVAST><pRedBCST>0.0000</pRedBCST><vBCST>113.22</vBCST><pICMSST>18.0000</pICMSST><vICMSST>10.98</vICMSST></ICMS10></ICMS><IPI><cEnq>999</cEnq><IPITrib><CST>99</CST><vBC>0.00</vBC><pIPI>0.0000</pIPI><vIPI>0.00</vIPI></IPITrib></IPI><PIS><PISAliq><CST>01</CST><vBC>68.81</vBC><pPIS>1.6500</pPIS><vPIS>1.14</vPIS></PISAliq></PIS><COFINS><COFINSAliq><CST>01</CST><vBC>68.81</vBC><pCOFINS>7.6000</pCOFINS><vCOFINS>5.23</vCOFINS></COFINSAliq></COFINS></imposto></det><det nItem="28"><prod><cProd>62154</cProd><cEAN>7897451468632</cEAN><xProd>DISCO DIAM TURBO 110MM PORCELANATO</xProd><NCM>68042119</NCM><CFOP>6102</CFOP><uCom>UN</uCom><qCom>10.0000</qCom><vUnCom>15.9800000000</vUnCom><vProd>159.80</vProd><cEANTrib>7897451468632</cEANTrib><uTrib>UN</uTrib><qTrib>10.0000</qTrib><vUnTrib>15.9800000000</vUnTrib><vOutro>0.51</vOutro><indTot>1</indTot><xPed>6787011444</xPed><nItemPed>28</nItemPed></prod><imposto><ICMS><ICMS00><orig>2</orig><CST>00</CST><modBC>3</modBC><vBC>160.31</vBC><pICMS>4.0000</pICMS><vICMS>6.41</vICMS></ICMS00></ICMS><IPI><cEnq>999</cEnq><IPITrib><CST>99</CST><vBC>0.00</vBC><pIPI>0.0000</pIPI><vIPI>0.00</vIPI></IPITrib></IPI><PIS><PISAliq><CST>01</CST><vBC>153.90</vBC><pPIS>1.6500</pPIS><vPIS>2.54</vPIS></PISAliq></PIS><COFINS><COFINSAliq><CST>01</CST><vBC>153.90</vBC><pCOFINS>7.6000</pCOFINS><vCOFINS>11.70</vCOFINS></COFINSAliq></COFINS></imposto></det><det nItem="29"><prod><cProd>68141</cProd><cEAN>7898547052223</cEAN><xProd>DISCO DIAM SEGM 105MM P/CONCRETO</xProd><NCM>68042119</NCM><CFOP>6102</CFOP><uCom>UN</uCom><qCom>20.0000</qCom><vUnCom>6.1800000000</vUnCom><vProd>123.60</vProd><cEANTrib>7898547052223</cEANTrib><uTrib>UN</uTrib><qTrib>20.0000</qTrib><vUnTrib>6.1800000000</vUnTrib><vOutro>0.26</vOutro><indTot>1</indTot><xPed>6787011444</xPed><nItemPed>29</nItemPed></prod><imposto><ICMS><ICMS00><orig>2</orig><CST>00</CST><modBC>3</modBC><vBC>123.86</vBC><pICMS>4.0000</pICMS><vICMS>4.95</vICMS></ICMS00></ICMS><IPI><cEnq>999</cEnq><IPITrib><CST>99</CST><vBC>0.00</vBC><pIPI>0.0000</pIPI><vIPI>0.00</vIPI></IPITrib></IPI><PIS><PISAliq><CST>01</CST><vBC>118.91</vBC><pPIS>1.6500</pPIS><vPIS>1.96</vPIS></PISAliq></PIS><COFINS><COFINSAliq><CST>01</CST><vBC>118.91</vBC><pCOFINS>7.6000</pCOFINS><vCOFINS>9.04</vCOFINS></COFINSAliq></COFINS></imposto></det><det nItem="30"><prod><cProd>68142</cProd><cEAN>7898547051783</cEAN><xProd>DISCO DIAM TURBO 105MM</xProd><NCM>68042190</NCM><CFOP>6102</CFOP><uCom>UN</uCom><qCom>10.0000</qCom><vUnCom>6.2800000000</vUnCom><vProd>62.80</vProd><cEANTrib>7898547051783</cEANTrib><uTrib>UN</uTrib><qTrib>10.0000</qTrib><vUnTrib>6.2800000000</vUnTrib><vOutro>0.13</vOutro><indTot>1</indTot><xPed>6787011444</xPed><nItemPed>30</nItemPed></prod><imposto><ICMS><ICMS00><orig>2</orig><CST>00</CST><modBC>3</modBC><vBC>62.93</vBC><pICMS>4.0000</pICMS><vICMS>2.52</vICMS></ICMS00></ICMS><IPI><cEnq>999</cEnq><IPITrib><CST>99</CST><vBC>0.00</vBC><pIPI>0.0000</pIPI><vIPI>0.00</vIPI></IPITrib></IPI><PIS><PISAliq><CST>01</CST><vBC>60.41</vBC><pPIS>1.6500</pPIS><vPIS>1.00</vPIS></PISAliq></PIS><COFINS><COFINSAliq><CST>01</CST><vBC>60.41</vBC><pCOFINS>7.6000</pCOFINS><vCOFINS>4.59</vCOFINS></COFINSAliq></COFINS></imposto></det><det nItem="31"><prod><cProd>70584</cProd><cEAN>7896689113345</cEAN><xProd>SUPORTE P/TV PLASMA/LCD UNIVERSAL FIXO</xProd><NCM>73269090</NCM><CFOP>6102</CFOP><uCom>UN</uCom><qCom>5.0000</qCom><vUnCom>12.0400000000</vUnCom><vProd>60.20</vProd><cEANTrib>7896689113345</cEANTrib><uTrib>UN</uTrib><qTrib>5.0000</qTrib><vUnTrib>12.0400000000</vUnTrib><vOutro>0.13</vOutro><indTot>1</indTot><xPed>6787011444</xPed><nItemPed>31</nItemPed></prod><imposto><ICMS><ICMS00><orig>0</orig><CST>00</CST><modBC>3</modBC><vBC>60.33</vBC><pICMS>12.0000</pICMS><vICMS>7.24</vICMS></ICMS00></ICMS><IPI><cEnq>999</cEnq><IPITrib><CST>99</CST><vBC>0.00</vBC><pIPI>0.0000</pIPI><vIPI>0.00</vIPI></IPITrib></IPI><PIS><PISAliq><CST>01</CST><vBC>53.09</vBC><pPIS>1.6500</pPIS><vPIS>0.88</vPIS></PISAliq></PIS><COFINS><COFINSAliq><CST>01</CST><vBC>53.09</vBC><pCOFINS>7.6000</pCOFINS><vCOFINS>4.03</vCOFINS></COFINSAliq></COFINS></imposto></det><total><ICMSTot><vBC>1765.23</vBC><vICMS>140.82</vICMS><vICMSDeson>0.00</vICMSDeson><vFCP>0.00</vFCP><vBCST>607.94</vBCST><vST>61.22</vST><vFCPST>0.00</vFCPST><vFCPSTRet>0.00</vFCPSTRet><vProd>1774.46</vProd><vFrete>0.00</vFrete><vSeg>0.00</vSeg><vDesc>0.00</vDesc><vII>0.00</vII><vIPI>0.00</vIPI><vIPIDevol>0.00</vIPIDevol><vPIS>27.04</vPIS><vCOFINS>124.46</vCOFINS><vOutro>4.00</vOutro><vNF>1839.68</vNF><vTotTrib>0.00</vTotTrib></ICMSTot></total><transp><modFrete>0</modFrete><vol><qVol>9</qVol><nVol>9</nVol><pesoL>93.824</pesoL><pesoB>97.990</pesoB></vol></transp><cobr><fat><nFat>2736671</nFat><vOrig>1839.68</vOrig><vDesc>0</vDesc><vLiq>1839.68</vLiq></fat><dup><nDup>001</nDup><dVenc>2021-10-17</dVenc><vDup>1839.68</vDup></dup></cobr><pag><detPag><indPag>1</indPag><tPag>99</tPag><xPag>OUTROS</xPag><vPag>1839.68</vPag></detPag></pag><infAdic><infCpl>PEDIDO:6787011444 VOLUMES:9 QT.ITENS:31//63 99291-6366 Joo//Cod. Cliente.:358912NR. Pedido:6787011444Num. Trans.:8534183Num. Carreg.:1268374//Cod. Cob.: 237 Prazo: 14 DIAS//RCA:6787JOSUE DUARTE RIBEIRO//NAO PAGAR P/ REPRESENTANTE. ENTREGAR SOMENTE P/ TITULAR NO ENDERECO DESTA N.F OBRIGATORIA A CONFERENCIA NO ATO DO RECEBIMENTO. NAO ACEITAMOS DEVOLUCAO NEM RECLAMACO POSTERIOR. ATENCAO: Quadrilhas especializadas em crimes pela Internet estao fraudando boletos e, inclusive, ligando para os clientes. Prezado cliente, A Condor esclarece que nao envia informacoes financeiras e Boletos de Pagamento via e-mail ou skype sem a autorizacao do Cliente, nem autoriza terceiros a faze-lo. Lembra tambem a atualizacao de Boleto contido no nosso site e um link de direcionamento e que os boletos sao atualizados na plataforma do proprio Banco Bradesco. Caso receba alguma mensagem com as caracteristicas diferente da apresentada, apague-a imediatamente, NO PAGUE e desconsidere o boleto//EXCLUSAO DO ICMS NA BASE DE CALCULO DO PIS E COFINS CONFORME PROCESSO/MAND.SEGU N.10056276020154013400 DE 01/01/2014 VALOR EXCLUIDO DA BASE DE CALCULO R$ 140.82//EXCLUSO DO ICMS NA BASE DE CLCULO DO PIS E COFINS CONFORME PROCESSO/MAND.SEGU N.10056276020154013400 DE 01/01/2014 VALOR EXCLUIDO DA BASE DE CALCULO R$ 140.82//ICMS sobre o frete retido por Subst tribut, na formado subitem 1.2 do cad IV anexo IV Dec.18955/97////ICMS sobre o frete retido por Subst tribut, na formado subitem 1.2 do cad IV anexo IV Dec.18955/97</infCpl></infAdic><infRespTec><CNPJ>07577599000501</CNPJ><xContato>TOTVS BRASILIA SOFTWARE - UNIDADE GOIANIA LTDA</xContato><email>resp_tecnico_dfe_winthor@totvs.com.br</email><fone>06232500200</fone></infRespTec></infNFe><Signature xmlns="http://www.w3.org/2000/09/xmldsig#"><SignedInfo><CanonicalizationMethod Algorithm="http://www.w3.org/TR/2001/REC-xml-c14n-20010315" /><SignatureMethod Algorithm="http://www.w3.org/2000/09/xmldsig#rsa-sha1" /><Reference URI="#NFe53211003261204000336550010027366711491155622"><Transforms><Transform Algorithm="http://www.w3.org/2000/09/xmldsig#enveloped-signature" /><Transform Algorithm="http://www.w3.org/TR/2001/REC-xml-c14n-20010315" /></Transforms><DigestMethod Algorithm="http://www.w3.org/2000/09/xmldsig#sha1" /><DigestValue>PGjvuGlUFWfeoFggMv522ACNHBo=</DigestValue></Reference></SignedInfo><SignatureValue>EqNsGWuX+iO9omsRae9DETnKfNi+eBUZe8F9Bo+4/ADYcc6toCPzPAxRLidF6I72BxrrFyu9LUgE
Pvqep75epIZIHwAyXNaOci8ky79D6Bbk8qZvL2i8Hf7vZsDRtyTPlyb+2m6n7mdP9G7MNdH1VmNz
VyXKdZqkle/VUtWgo4jL11/DYMzqIVzed/dCfgbvPFSwxMhAjM7j2PK3YQ1xfRW5HYgUI12C4Moc
XT7AlmHM0p0U8olJoIAdbtEFVfiFx17IZ7Ow0RJCOiy0EQFSSQXykF2ESetS7LoPThrzuzRlIqJs
ZkOOGR+VVwOIxBfWvAKm+45UbAMXeImgXb2eeA==</SignatureValue><KeyInfo><X509Data><X509Certificate>MIIIMDCCBhigAwIBAgIIS7/v1VMSAXQwDQYJKoZIhvcNAQELBQAwdTELMAkGA1UEBhMCQlIxEzAR
BgNVBAoMCklDUC1CcmFzaWwxNjA0BgNVBAsMLVNlY3JldGFyaWEgZGEgUmVjZWl0YSBGZWRlcmFs
IGRvIEJyYXNpbCAtIFJGQjEZMBcGA1UEAwwQQUMgU0VSQVNBIFJGQiB2NTAeFw0yMTA4MjMxOTI3
MDBaFw0yMjA4MjMxOTI3MDBaMIIBQzELMAkGA1UEBhMCQlIxCzAJBgNVBAgMAkRGMRgwFgYDVQQH
DA9CcmFzw4PCg8OCwq1saWExEzARBgNVBAoMCklDUC1CcmFzaWwxGDAWBgNVBAsMDzAwMDAwMTAx
MDQ0OTM5NTE2MDQGA1UECwwtU2VjcmV0YXJpYSBkYSBSZWNlaXRhIEZlZGVyYWwgZG8gQnJhc2ls
IC0gUkZCMRYwFAYDVQQLDA1SRkIgZS1DTlBKIEExMRYwFAYDVQQLDA1BQyBTRVJBU0EgUkZCMRcw
FQYDVQQLDA4xMDg3MTA5MTAwMDE5NDETMBEGA1UECwwKUFJFU0VOQ0lBTDFIMEYGA1UEAww/Q09O
RE9SIEFUQUNBRElTVEEgREUgTUFURVJJQUlTIFBBUkEgQ09OU1RSVUNBTyBTOjAzMjYxMjA0MDAw
MTc0MIIBIjANBgkqhkiG9w0BAQEFAAOCAQ8AMIIBCgKCAQEAuLP2vnw8e1Dc5TrqUFlM0W3BlF9O
PXOoa3dGfSvoXXsPdk1LSE9Vnmzkj67strGxqR5DM/1gSVg0Gfpk0JVx0DiLCvTWVDqOMI5YYS3N
WlzrFNXOi4rCyGv9UevqeX/DzoIocbZ2RVlNjoobnQQNanDUmJ27trfPBZaLK8D6KAuM7NWD1kjm
MJyeTZmfYaDySiBkGLldC+hMAuWOc9bnlxEjXTtZsILcUkUuLGS7BEbXXsDA7E/IAvYKTbhrokkJ
tVIjH6IZmyGtPGzu7SgfUQUxCfE28CaqEczoXtkS4z/KCPrrX2NLTaAYm9ft6ED8vC+5o7l3im5v
uumgjcrTtwIDAQABo4IC8jCCAu4wCQYDVR0TBAIwADAfBgNVHSMEGDAWgBTs8UFRV6jmOules6Ai
+QiKtTqHjzCBmQYIKwYBBQUHAQEEgYwwgYkwSAYIKwYBBQUHMAKGPGh0dHA6Ly93d3cuY2VydGlm
aWNhZG9kaWdpdGFsLmNvbS5ici9jYWRlaWFzL3NlcmFzYXJmYnY1LnA3YjA9BggrBgEFBQcwAYYx
aHR0cDovL29jc3AuY2VydGlmaWNhZG9kaWdpdGFsLmNvbS5ici9zZXJhc2FyZmJ2NTCBwgYDVR0R
BIG6MIG3gRpHT01JREVAQ09ORE9SQlJBU0lMLkNPTS5CUqAlBgVgTAEDAqAcExpST0JFUlRPIEdP
TUlERSBDQVNUQU5IRUlSQaAZBgVgTAEDA6AQEw4wMzI2MTIwNDAwMDE3NKA+BgVgTAEDBKA1EzMx
MjA0MTk2MTIyMzIwNjEwMTk3MDAwMDAwMDAwMDAwMDAwMDAwMDAwMDAwMDAwMDAwMDCgFwYFYEwB
AwegDhMMMDAwMDAwMDAwMDAwMHEGA1UdIARqMGgwZgYGYEwBAgENMFwwWgYIKwYBBQUHAgEWTmh0
dHA6Ly9wdWJsaWNhY2FvLmNlcnRpZmljYWRvZGlnaXRhbC5jb20uYnIvcmVwb3NpdG9yaW8vZHBj
L2RlY2xhcmFjYW8tcmZiLnBkZjAdBgNVHSUEFjAUBggrBgEFBQcDAgYIKwYBBQUHAwQwgZ0GA1Ud
HwSBlTCBkjBKoEigRoZEaHR0cDovL3d3dy5jZXJ0aWZpY2Fkb2RpZ2l0YWwuY29tLmJyL3JlcG9z
aXRvcmlvL2xjci9zZXJhc2FyZmJ2NS5jcmwwRKBCoECGPmh0dHA6Ly9sY3IuY2VydGlmaWNhZG9z
LmNvbS5ici9yZXBvc2l0b3Jpby9sY3Ivc2VyYXNhcmZidjUuY3JsMB0GA1UdDgQWBBQt4NJpVwxh
L1+7IZpLqNe0mWW15jAOBgNVHQ8BAf8EBAMCBeAwDQYJKoZIhvcNAQELBQADggIBABoC/83kG/gr
+VkUdsaAmH1JybTtaTA04Zgq9jvHl9FC+yUOIPWYO2cm+8Q+/juqvRQK9+MVR0H/0do5gH1Ye6oF
mExLbewWX16cKtaDKGpnfb609rW4VZdUrn5zSl1+7zaWNeFmrJb5onWqt/bfGMrAqxQ2IcajGdoS
k27gROo8jk6+5toYsNz+o/oNJeryF6SE9Wu2/KiShTDr+411d5PA044H53H8/CKE21LMozTbf1CW
w9mAjbqXJqgoYRGF2/xymih26dgDgXKkR7By1bl+MdjeAneyRqs20ZBy1pPK+kYC1aQlEA2lC3lD
6glZN4WW/gPS73HuMITY7gnP8Di3Wvi2j6sJKJoz+NAtmrtqhZ6Mb1vMBP7NPMTVy1oCpn+YKmL/
f+nnTALBsmJZBEMgVwvwbb1VmS/PwXvAO/5ppmRasog/t8oTPmSkTuPW6V4Jh/vMctVh4iGduxaA
sTLYlVrNuDsowgWJbVCxi59JEIP4Sfk2XzMdW4upicVJacJdyeZMSp0kdO63FlViB671BfFs7/g/
Wc81qFKye95mcT13B9m7HhspWUBKoOb/vpY0AirkVPv4UkWpyjXktr1+MercAeDy6QC+tDmAA0i9
8XDM5PLjNszBojKAyFvvVG5qiRjAHWAxx5IftPmAltxB6fyD2K2GcMEFznE/ftUN</X509Certificate></X509Data></KeyInfo></Signature></NFe><protNFe versao="4.00" xmlns="http://www.portalfiscal.inf.br/nfe"><infProt><tpAmb>1</tpAmb><verAplic>SVRS202110010759</verAplic><chNFe>53211003261204000336550010027366711491155622</chNFe><dhRecbto>2021-10-03T10:09:38-03:00</dhRecbto><nProt>353210053437176</nProt><digVal>PGjvuGlUFWfeoFggMv522ACNHBo=</digVal><cStat>100</cStat><xMotivo>Autorizado o uso da NF-e</xMotivo></infProt></protNFe></nfeProc>